jsonsimpleconfig/__init__.py
jsonsimpleconfig/jsc2json.py
jsonsimpleconfig/jsc_print.py
jsonsimpleconfig/jsc_value.py
jsonsimpleconfig/jsccommon/__init__.py
jsonsimpleconfig/jsccommon/jsc_comments.py
jsonsimpleconfig/jsccommon/jsc_common.py
jsonsimpleconfig/jscdata/__init__.py
jsonsimpleconfig/jscdata/flat_data.py
jsonsimpleconfig/jscdata/jsc_data.py
jsonsimpleconfig/jscdata/jsc_section.py
jsonsimpleconfig/jscextractor/__init__.py
jsonsimpleconfig/jscextractor/jsc_extractor.py
jsonsimpleconfig/jscextractor/jsc_header.py
jsonsimpleconfig/jscextractor/json_extractor.py
jsonsimpleconfig/jschelper/__init__.py
jsonsimpleconfig/jschelper/jsc.py
jsonsimpleconfig/jschelper/jsc2json_helper.py
jsonsimpleconfig/jschelper/jsc_config.py
jsonsimpleconfig/jschelper/jsc_managed_config.py
jsonsimpleconfig/jschelper/json2csv_helper.py
jsonsimpleconfig/jschelper/json2jsc_helper.py
jsonsimpleconfig/jscparser/__init__.py
jsonsimpleconfig/jscparser/jsc_parser.py
jsonsimpleconfig/jscparser/json.py
jsonsimpleconfig/jscresources/defaultHeader.template
jsonsimpleconfig/json2csv.py
jsonsimpleconfig/json2jsc.py
poetry.lock
requirements.txt
jsonsimpleconfig-0.6.dist-info/entry_points.txt
jsonsimpleconfig-0.6.dist-info/LICENSE
jsonsimpleconfig-0.6.dist-info/WHEEL
jsonsimpleconfig-0.6.dist-info/METADATA
jsonsimpleconfig-0.6.dist-info/RECORD
